[
  {
    "id": "business-analyst",
    "name": "Business Analyst",
    "personaName": "Ananya Verma",
    "icon": "FileEdit",
    "capabilities": ["rule.view", "rule.create", "rule.edit", "rule.simulate", "notifyx.view"]
  },
  {
    "id": "product-manager",
    "name": "Product Manager",
    "personaName": "Rohan Mehta",
    "icon": "Briefcase",
    "capabilities": ["rule.view", "rule.create", "rule.edit", "rule.simulate", "rule.publish", "config.manage", "notifyx.view", "notifyx.create", "notifyx.edit", "notifyx.toggle"]
  },
  {
    "id": "risk-manager",
    "name": "Credit/Risk Manager",
    "personaName": "Kavita Rao",
    "icon": "ShieldCheck",
    "capabilities": ["rule.view", "rule.create", "rule.edit", "rule.simulate", "rule.publish", "notifyx.view", "notifyx.toggle"]
  },
  {
    "id": "underwriter",
    "name": "Underwriter/Claims",
    "personaName": "Arjun Nair",
    "icon": "FileCheck2",
    "capabilities": ["rule.view", "rule.create", "rule.edit", "rule.simulate", "rule.publish", "notifyx.view"]
  },
  {
    "id": "operations",
    "name": "Operations",
    "personaName": "Divya Iyer",
    "icon": "Headphones",
    "capabilities": ["rule.view", "rule.simulate", "notifyx.view", "notifyx.toggle"]
  },
  {
    "id": "sysadmin",
    "name": "System Administrator",
    "personaName": "Vikram Chawla",
    "icon": "Settings",
    "capabilities": ["rule.view", "rule.create", "rule.edit", "rule.delete", "rule.simulate", "rule.publish", "system.manage", "config.manage", "notifyx.view", "notifyx.create", "notifyx.edit", "notifyx.toggle"]
  }
]
